odoo/addons/sale_product_set_variant/README.rst
odoo/addons/sale_product_set_variant/__init__.py
odoo/addons/sale_product_set_variant/__manifest__.py
odoo/addons/sale_product_set_variant/demo/product_set.xml
odoo/addons/sale_product_set_variant/models/__init__.py
odoo/addons/sale_product_set_variant/models/product_set_line.py
odoo/addons/sale_product_set_variant/static/description/add_set.png
odoo/addons/sale_product_set_variant/static/description/icon.png
odoo/addons/sale_product_set_variant/static/description/icon.svg
odoo/addons/sale_product_set_variant/static/description/product_set.png
odoo/addons/sale_product_set_variant/static/description/sale_order.png
odoo/addons/sale_product_set_variant/tests/__init__.py
odoo/addons/sale_product_set_variant/tests/test_product_set.py
odoo/addons/sale_product_set_variant/views/product_set.xml
odoo/addons/sale_product_set_variant/wizard/__init__.py
odoo/addons/sale_product_set_variant/wizard/product_set_add.py
odoo/addons/sale_product_set_variant/wizard/product_set_add.xml
odoo11_addon_sale_product_set_variant-11.0.1.0.0.dist-info/DESCRIPTION.rst
odoo11_addon_sale_product_set_variant-11.0.1.0.0.dist-info/METADATA
odoo11_addon_sale_product_set_variant-11.0.1.0.0.dist-info/RECORD
odoo11_addon_sale_product_set_variant-11.0.1.0.0.dist-info/WHEEL
odoo11_addon_sale_product_set_variant-11.0.1.0.0.dist-info/metadata.json
odoo11_addon_sale_product_set_variant-11.0.1.0.0.dist-info/top_level.txt
